pyNexafs/__init__.py
pyNexafs/__main__.py
pyNexafs/resources.py
pyNexafs/gui/__init__.py
pyNexafs/gui/data_browser.py
pyNexafs/gui/qant_converter.py
pyNexafs/gui/icons/normalisation.pdn
pyNexafs/gui/icons/normalisation.png
pyNexafs/gui/icons/normalisation2_dark.pdn
pyNexafs/gui/icons/normalisation2_dark.png
pyNexafs/gui/icons/normalisation2_light.pdn
pyNexafs/gui/icons/normalisation2_light.png
pyNexafs/gui/icons/flaticon/normalization.png
pyNexafs/gui/icons/flaticon/normalization_b&w.png
pyNexafs/gui/widgets/__init__.py
pyNexafs/gui/widgets/converter.py
pyNexafs/gui/widgets/fileloader.py
pyNexafs/gui/widgets/normaliser.py.old
pyNexafs/gui/widgets/reducer.py
pyNexafs/gui/widgets/viewer.py
pyNexafs/gui/widgets/fitting/nexafs_fits.py
pyNexafs/gui/widgets/graphing/__init__.py
pyNexafs/gui/widgets/graphing/plotly_graphs.py
pyNexafs/gui/widgets/graphing/matplotlib/graphs.py
pyNexafs/gui/widgets/graphing/matplotlib/styling.py
pyNexafs/gui/widgets/graphing/matplotlib/widgets.py
pyNexafs/gui/widgets/io/__init__.py
pyNexafs/gui/widgets/io/dir_selection.py
pyNexafs/gui/widgets/io/fileviewer.py
pyNexafs/nexafs/__init__.py
pyNexafs/nexafs/scan.py
pyNexafs/nexafs/fitting/functions.py
pyNexafs/nexafs/normalisation/__init__.py
pyNexafs/nexafs/normalisation/norm_settings.py
pyNexafs/nexafs/normalisation/scan_normalised.py
pyNexafs/parsers/__init__.py
pyNexafs/parsers/_base.py
pyNexafs/parsers/au/__init__.py
pyNexafs/parsers/au/aus_sync/MEX1.py
pyNexafs/parsers/au/aus_sync/MEX1_relabels.py
pyNexafs/parsers/au/aus_sync/MEX2.py
pyNexafs/parsers/au/aus_sync/MEX2_relabels.py
pyNexafs/parsers/au/aus_sync/SXR.py
pyNexafs/parsers/au/aus_sync/__init__.py
pyNexafs/utils/__init__.py
pyNexafs/utils/decorators.py
pyNexafs/utils/mda.py
pyNexafs/utils/reduction.py
pyNexafs/utils/sizes.py
pynexafs-0.1.0rc1.dist-info/licenses/LICENSE
pynexafs-0.1.0rc1.dist-info/METADATA
pynexafs-0.1.0rc1.dist-info/WHEEL
pynexafs-0.1.0rc1.dist-info/top_level.txt
pynexafs-0.1.0rc1.dist-info/RECORD
