Metadata-Version: 2.4
Name: pyNexafs
Version: 0.1.0rc1
Summary: A package for processing and analysing NEXAFS data.
Author-email: Matthew Gebert <matthew.gebert@monash.edu>
Maintainer-email: Matthew Gebert <matthew.gebert@monash.edu>
License: MIT License
Project-URL: code, https://github.com/xraysoftmat/pyNexafs
Project-URL: documentation, https://pyNexafs.readthedocs.io/en/latest/
Keywords: NEXAFS,XANES,Near,Edge,X-ray,Absorption,Fine,Structure,Spectroscopy,Optical Data,XAS,Synchrotron
Requires-Python: >=3.11
License-File: LICENSE
Requires-Dist: numpy
Requires-Dist: overrides
Requires-Dist: scipy
Requires-Dist: xdrlib3
Dynamic: license-file
